main.py
filesort-0.1.4.dist-info/LICENSE
filesort-0.1.4.dist-info/METADATA
filesort-0.1.4.dist-info/WHEEL
filesort-0.1.4.dist-info/entry_points.txt
filesort-0.1.4.dist-info/top_level.txt
filesort-0.1.4.dist-info/RECORD
