Metadata-Version: 2.1
Name: filesort
Version: 0.1.4
Summary: A package that aids sorting of files
Home-page: https://github.com/viv-codes/filesort
Author: Vivian Hafener
Author-email: vhafener@outlook.com
License: UNKNOWN
Project-URL: Bug Tracker, https://github.com/viv-codes/filesort/issues
Platform: UNKNOWN
Classifier: Programming Language :: Python :: 3
Classifier: License :: OSI Approved :: MIT License
Classifier: Operating System :: OS Independent
Requires-Python: >=3.6
License-File: LICENSE
Requires-Dist: Click
Requires-Dist: prompt-toolkit
Requires-Dist: yaspin
